aimsg/__init__.py
aimsg/cli.py
aimsg/config.py
aimsg/git_utils.py
aimsg/openai_utils.py
aimsg/utils.py
aimsg-0.2.3.dist-info/METADATA
aimsg-0.2.3.dist-info/WHEEL
aimsg-0.2.3.dist-info/entry_points.txt
aimsg-0.2.3.dist-info/top_level.txt
aimsg-0.2.3.dist-info/RECORD
