Metadata-Version: 2.2
Name: aimsg
Version: 0.2.3
Summary: A CLI tool to generate commit messages using AI models
Home-page: https://github.com/yurentle/aimsg
Author: yurentle
Author-email: yurentle <yurentle@gmail.com>
License: MIT
Project-URL: Homepage, https://github.com/yurentle/aimsg
Project-URL: Bug Tracker, https://github.com/yurentle/aimsg/issues
Project-URL: Repository, https://github.com/yurentle/aimsg.git
Keywords: git,commit,message,openai,gpt,cli,ai,deepseek
Classifier: Development Status :: 4 - Beta
Classifier: Environment :: Console
Classifier: Intended Audience :: Developers
Classifier: License :: OSI Approved :: MIT License
Classifier: Operating System :: OS Independent
Classifier: Programming Language :: Python :: 3
Classifier: Programming Language :: Python :: 3.7
Classifier: Programming Language :: Python :: 3.8
Classifier: Programming Language :: Python :: 3.9
Classifier: Programming Language :: Python :: 3.10
Classifier: Programming Language :: Python :: 3.11
Classifier: Programming Language :: Python :: 3.12
Classifier: Topic :: Software Development :: Libraries :: Python Modules
Classifier: Topic :: Software Development :: Version Control :: Git
Requires-Python: >=3.7
Requires-Dist: openai>=1.0.0
Requires-Dist: gitpython>=3.1.40
Requires-Dist: python-dotenv>=1.0.0
Requires-Dist: click>=8.1.7
Dynamic: author
Dynamic: home-page
Dynamic: requires-python
